{
    "packages": {
        "ho-nl/ho_import": [
            {
                "name": "ho-nl/ho_import",
                "version": "1.1",
                "version_normalized": "1.1.0.0",
                "source": {
                    "type": "git",
                    "url": "https://github.com/ho-nl/magento1-Ho_Import.git",
                    "reference": "4a4125e5fe86feb75b07145ee769bcd38a35adf8"
                },
                "dist": {
                    "type": "zip",
                    "url": "https://api.github.com/repos/ho-nl/magento1-Ho_Import/zipball/4a4125e5fe86feb75b07145ee769bcd38a35adf8",
                    "reference": "4a4125e5fe86feb75b07145ee769bcd38a35adf8",
                    "shasum": ""
                },
                "require": {
                    "avstudnitz/fast-simple-import": "dev-master",
                    "magento-hackathon/magento-composer-installer": "dev-master"
                },
                "time": "2014-02-15T12:39:26+00:00",
                "type": "magento-module",
                "description": "A Magento Module that allows you to map fields and import all sorts of file formats, sources and entities. Fast and Low Memory.",
                "homepage": "https://github.com/ho-nl/Ho_Import",
                "support": {
                    "source": "https://github.com/ho-nl/magento1-Ho_Import/tree/1.1",
                    "issues": "https://github.com/ho-nl/magento1-Ho_Import/issues"
                }
            },
            {
                "name": "ho-nl/ho_import",
                "version": "1.2",
                "version_normalized": "1.2.0.0",
                "source": {
                    "type": "git",
                    "url": "https://github.com/ho-nl/magento1-Ho_Import.git",
                    "reference": "d375da0ee62892cdea8bf08a02c31b0985d39b8b"
                },
                "dist": {
                    "type": "zip",
                    "url": "https://api.github.com/repos/ho-nl/magento1-Ho_Import/zipball/d375da0ee62892cdea8bf08a02c31b0985d39b8b",
                    "reference": "d375da0ee62892cdea8bf08a02c31b0985d39b8b",
                    "shasum": ""
                },
                "require": {
                    "avstudnitz/fast-simple-import": "dev-master",
                    "magento-hackathon/magento-composer-installer": "dev-master"
                },
                "time": "2014-05-05T11:40:44+00:00",
                "type": "magento-module",
                "description": "A Magento Module that allows you to map fields and import all sorts of file formats, sources and entities. Fast and Low Memory.",
                "homepage": "https://github.com/ho-nl/Ho_Import",
                "support": {
                    "source": "https://github.com/ho-nl/magento1-Ho_Import/tree/1.2",
                    "issues": "https://github.com/ho-nl/magento1-Ho_Import/issues"
                }
            },
            {
                "name": "ho-nl/ho_import",
                "version": "1.3",
                "version_normalized": "1.3.0.0",
                "source": {
                    "type": "git",
                    "url": "https://github.com/ho-nl/magento1-Ho_Import.git",
                    "reference": "75e4729aca03e5c142f8f7f75ea2e42058cabeb1"
                },
                "dist": {
                    "type": "zip",
                    "url": "https://api.github.com/repos/ho-nl/magento1-Ho_Import/zipball/75e4729aca03e5c142f8f7f75ea2e42058cabeb1",
                    "reference": "75e4729aca03e5c142f8f7f75ea2e42058cabeb1",
                    "shasum": ""
                },
                "require": {
                    "avstudnitz/fast-simple-import": "dev-master",
                    "magento-hackathon/magento-composer-installer": "dev-master"
                },
                "time": "2014-06-18T08:58:15+00:00",
                "type": "magento-module",
                "description": "A Magento Module that allows you to map fields and import all sorts of file formats, sources and entities. Fast and Low Memory.",
                "homepage": "https://github.com/ho-nl/Ho_Import",
                "support": {
                    "source": "https://github.com/ho-nl/magento1-Ho_Import/tree/1.3",
                    "issues": "https://github.com/ho-nl/magento1-Ho_Import/issues"
                }
            },
            {
                "name": "ho-nl/ho_import",
                "version": "1.4",
                "version_normalized": "1.4.0.0",
                "source": {
                    "type": "git",
                    "url": "https://github.com/ho-nl/magento1-Ho_Import.git",
                    "reference": "d2cfbb076fec37d61e2a5b479fdda7b2e7217456"
                },
                "dist": {
                    "type": "zip",
                    "url": "https://api.github.com/repos/ho-nl/magento1-Ho_Import/zipball/d2cfbb076fec37d61e2a5b479fdda7b2e7217456",
                    "reference": "d2cfbb076fec37d61e2a5b479fdda7b2e7217456",
                    "shasum": ""
                },
                "require": {
                    "avstudnitz/fast-simple-import": "*",
                    "magento-hackathon/magento-composer-installer": "*"
                },
                "time": "2014-09-01T09:34:56+00:00",
                "type": "magento-module",
                "license": [
                    "OSL-3.0"
                ],
                "authors": [
                    {
                        "name": "Paul Hachmang - H&O",
                        "email": "paul@h-o.nl"
                    }
                ],
                "description": "A Magento Module that allows you to map fields and import all sorts of file formats, sources and entities. Fast and Low Memory.",
                "homepage": "https://github.com/ho-nl/Ho_Import",
                "support": {
                    "source": "https://github.com/ho-nl/magento1-Ho_Import/tree/1.4",
                    "issues": "https://github.com/ho-nl/magento1-Ho_Import/issues"
                }
            },
            {
                "name": "ho-nl/ho_import",
                "version": "1.5",
                "version_normalized": "1.5.0.0",
                "source": {
                    "type": "git",
                    "url": "https://github.com/ho-nl/magento1-Ho_Import.git",
                    "reference": "9fdd2876bce0249ebbbf556244ba1ce608ae02ca"
                },
                "dist": {
                    "type": "zip",
                    "url": "https://api.github.com/repos/ho-nl/magento1-Ho_Import/zipball/9fdd2876bce0249ebbbf556244ba1ce608ae02ca",
                    "reference": "9fdd2876bce0249ebbbf556244ba1ce608ae02ca",
                    "shasum": ""
                },
                "require": {
                    "avstudnitz/fast-simple-import": "*",
                    "magento-hackathon/magento-composer-installer": "*"
                },
                "time": "2014-09-18T13:50:52+00:00",
                "type": "magento-module",
                "license": [
                    "OSL-3.0"
                ],
                "authors": [
                    {
                        "name": "Paul Hachmang - H&O",
                        "email": "paul@h-o.nl"
                    }
                ],
                "description": "A Magento Module that allows you to map fields and import all sorts of file formats, sources and entities. Fast and Low Memory.",
                "homepage": "https://github.com/ho-nl/Ho_Import",
                "support": {
                    "source": "https://github.com/ho-nl/magento1-Ho_Import/tree/1.5",
                    "issues": "https://github.com/ho-nl/magento1-Ho_Import/issues"
                }
            },
            {
                "name": "ho-nl/ho_import",
                "version": "1.6",
                "version_normalized": "1.6.0.0",
                "source": {
                    "type": "git",
                    "url": "https://github.com/ho-nl/magento1-Ho_Import.git",
                    "reference": "27a1fd8e57fd858825bbde152a3afb87b1be774b"
                },
                "dist": {
                    "type": "zip",
                    "url": "https://api.github.com/repos/ho-nl/magento1-Ho_Import/zipball/27a1fd8e57fd858825bbde152a3afb87b1be774b",
                    "reference": "27a1fd8e57fd858825bbde152a3afb87b1be774b",
                    "shasum": ""
                },
                "require": {
                    "avstudnitz/fast-simple-import": "*",
                    "magento-hackathon/magento-composer-installer": "*"
                },
                "time": "2015-05-03T11:52:05+00:00",
                "type": "magento-module",
                "license": [
                    "OSL-3.0"
                ],
                "authors": [
                    {
                        "name": "Paul Hachmang - H&O",
                        "email": "paul@h-o.nl"
                    }
                ],
                "description": "A Magento Module that allows you to map fields and import all sorts of file formats, sources and entities. Fast and Low Memory.",
                "homepage": "https://github.com/ho-nl/Ho_Import",
                "support": {
                    "source": "https://github.com/ho-nl/magento1-Ho_Import/tree/1.6",
                    "issues": "https://github.com/ho-nl/magento1-Ho_Import/issues"
                }
            },
            {
                "name": "ho-nl/ho_import",
                "version": "1.6.1",
                "version_normalized": "1.6.1.0",
                "source": {
                    "type": "git",
                    "url": "https://github.com/ho-nl/magento1-Ho_Import.git",
                    "reference": "bd1d407e1054568baf51b55a5f9b8e79bff07a9d"
                },
                "dist": {
                    "type": "zip",
                    "url": "https://api.github.com/repos/ho-nl/magento1-Ho_Import/zipball/bd1d407e1054568baf51b55a5f9b8e79bff07a9d",
                    "reference": "bd1d407e1054568baf51b55a5f9b8e79bff07a9d",
                    "shasum": ""
                },
                "require": {
                    "avstudnitz/fast-simple-import": "*",
                    "magento-hackathon/magento-composer-installer": "*"
                },
                "time": "2015-05-04T09:46:14+00:00",
                "type": "magento-module",
                "license": [
                    "OSL-3.0"
                ],
                "authors": [
                    {
                        "name": "Paul Hachmang - H&O",
                        "email": "paul@h-o.nl"
                    }
                ],
                "description": "A Magento Module that allows you to map fields and import all sorts of file formats, sources and entities. Fast and Low Memory.",
                "homepage": "https://github.com/ho-nl/Ho_Import",
                "support": {
                    "source": "https://github.com/ho-nl/magento1-Ho_Import/tree/1.6.1",
                    "issues": "https://github.com/ho-nl/magento1-Ho_Import/issues"
                }
            },
            {
                "name": "ho-nl/ho_import",
                "version": "1.6.2",
                "version_normalized": "1.6.2.0",
                "source": {
                    "type": "git",
                    "url": "https://github.com/ho-nl/magento1-Ho_Import.git",
                    "reference": "58166319bb08e067810e53cac5d2370da1c06cf9"
                },
                "dist": {
                    "type": "zip",
                    "url": "https://api.github.com/repos/ho-nl/magento1-Ho_Import/zipball/58166319bb08e067810e53cac5d2370da1c06cf9",
                    "reference": "58166319bb08e067810e53cac5d2370da1c06cf9",
                    "shasum": ""
                },
                "require": {
                    "avstudnitz/fast-simple-import": "*",
                    "magento-hackathon/magento-composer-installer": "*"
                },
                "time": "2015-11-06T13:17:57+00:00",
                "type": "magento-module",
                "license": [
                    "OSL-3.0"
                ],
                "authors": [
                    {
                        "name": "Paul Hachmang - H&O",
                        "email": "paul@h-o.nl"
                    }
                ],
                "description": "A Magento Module that allows you to map fields and import all sorts of file formats, sources and entities. Fast and Low Memory.",
                "homepage": "https://github.com/ho-nl/Ho_Import",
                "support": {
                    "source": "https://github.com/ho-nl/magento1-Ho_Import/tree/1.6.2",
                    "issues": "https://github.com/ho-nl/magento1-Ho_Import/issues"
                }
            },
            {
                "name": "ho-nl/ho_import",
                "version": "1.7",
                "version_normalized": "1.7.0.0",
                "source": {
                    "type": "git",
                    "url": "https://github.com/ho-nl/magento1-Ho_Import.git",
                    "reference": "33245c24218dfb254735e06a28e7a530406bb180"
                },
                "dist": {
                    "type": "zip",
                    "url": "https://api.github.com/repos/ho-nl/magento1-Ho_Import/zipball/33245c24218dfb254735e06a28e7a530406bb180",
                    "reference": "33245c24218dfb254735e06a28e7a530406bb180",
                    "shasum": ""
                },
                "require": {
                    "avstudnitz/fast-simple-import": "*",
                    "magento-hackathon/magento-composer-installer": "*"
                },
                "time": "2016-06-09T12:08:30+00:00",
                "type": "magento-module",
                "license": [
                    "OSL-3.0"
                ],
                "authors": [
                    {
                        "name": "Paul Hachmang - H&O",
                        "email": "paul@h-o.nl"
                    }
                ],
                "description": "A Magento Module that allows you to map fields and import all sorts of file formats, sources and entities. Fast and Low Memory.",
                "homepage": "https://github.com/ho-nl/Ho_Import",
                "support": {
                    "source": "https://github.com/ho-nl/magento1-Ho_Import/tree/1.7",
                    "issues": "https://github.com/ho-nl/magento1-Ho_Import/issues"
                }
            },
            {
                "name": "ho-nl/ho_import",
                "version": "1.7.1",
                "version_normalized": "1.7.1.0",
                "source": {
                    "type": "git",
                    "url": "https://github.com/ho-nl/magento1-Ho_Import.git",
                    "reference": "fbd33f403a301d82b1492a1222bc0f3c3d52342d"
                },
                "dist": {
                    "type": "zip",
                    "url": "https://api.github.com/repos/ho-nl/magento1-Ho_Import/zipball/fbd33f403a301d82b1492a1222bc0f3c3d52342d",
                    "reference": "fbd33f403a301d82b1492a1222bc0f3c3d52342d",
                    "shasum": ""
                },
                "require": {
                    "avstudnitz/fast-simple-import": "*",
                    "magento-hackathon/magento-composer-installer": "*"
                },
                "time": "2016-11-28T10:34:33+00:00",
                "type": "magento-module",
                "license": [
                    "OSL-3.0"
                ],
                "authors": [
                    {
                        "name": "Paul Hachmang - H&O",
                        "email": "paul@h-o.nl"
                    }
                ],
                "description": "A Magento Module that allows you to map fields and import all sorts of file formats, sources and entities. Fast and Low Memory.",
                "homepage": "https://github.com/ho-nl/Ho_Import",
                "support": {
                    "source": "https://github.com/ho-nl/magento1-Ho_Import/tree/1.7.1",
                    "issues": "https://github.com/ho-nl/magento1-Ho_Import/issues"
                }
            },
            {
                "name": "ho-nl/ho_import",
                "version": "1.7.2",
                "version_normalized": "1.7.2.0",
                "source": {
                    "type": "git",
                    "url": "https://github.com/ho-nl/magento1-Ho_Import.git",
                    "reference": "5437a217aba9361c0dd7ff10c97f379f4056e8a6"
                },
                "dist": {
                    "type": "zip",
                    "url": "https://api.github.com/repos/ho-nl/magento1-Ho_Import/zipball/5437a217aba9361c0dd7ff10c97f379f4056e8a6",
                    "reference": "5437a217aba9361c0dd7ff10c97f379f4056e8a6",
                    "shasum": ""
                },
                "require": {
                    "avstudnitz/fast-simple-import": "*",
                    "magento-hackathon/magento-composer-installer": "*"
                },
                "time": "2017-07-07T07:39:08+00:00",
                "type": "magento-module",
                "license": [
                    "OSL-3.0"
                ],
                "authors": [
                    {
                        "name": "Paul Hachmang - H&O",
                        "email": "paul@h-o.nl"
                    }
                ],
                "description": "A Magento Module that allows you to map fields and import all sorts of file formats, sources and entities. Fast and Low Memory.",
                "homepage": "https://github.com/ho-nl/Ho_Import",
                "support": {
                    "source": "https://github.com/ho-nl/magento1-Ho_Import/tree/1.7.2",
                    "issues": "https://github.com/ho-nl/magento1-Ho_Import/issues"
                }
            }
        ]
    }
}
