{
    "packages": {
        "connect20/ajax_editable_category_product": [
            {
                "name": "connect20/Ajax_Editable_Category_Product",
                "version": "1.0.1",
                "version_normalized": "1.0.1.0",
                "dist": {
                    "type": "tar",
                    "url": "https://connect20.magentocommerce.com/community/Ajax_Editable_Category_Product/1.0.1/Ajax_Editable_Category_Product-1.0.1.tgz"
                },
                "suggest": {
                    "magento-hackathon/magento-composer-installer": "Allows to manage this package as a dependency"
                },
                "type": "magento-module",
                "extra": {
                    "package-xml": "package.xml"
                },
                "license": [
                    "Open-Software-License-(OSL)"
                ],
                "authors": [
                    {
                        "name": "Anupam Tiwari",
                        "email": "vishwasnature30@gmail.com"
                    }
                ],
                "description": "Ajax Editable Category Product allows you to quick update products from category section."
            },
            {
                "name": "connect20/Ajax_Editable_Category_Product",
                "version": "1.0.2",
                "version_normalized": "1.0.2.0",
                "dist": {
                    "type": "tar",
                    "url": "https://connect20.magentocommerce.com/community/Ajax_Editable_Category_Product/1.0.2/Ajax_Editable_Category_Product-1.0.2.tgz"
                },
                "suggest": {
                    "magento-hackathon/magento-composer-installer": "Allows to manage this package as a dependency"
                },
                "type": "magento-module",
                "extra": {
                    "package-xml": "package.xml"
                },
                "license": [
                    "Open-Software-License-(OSL)"
                ],
                "authors": [
                    {
                        "name": "Anupam Tiwari",
                        "email": "vishwasnature30@gmail.com"
                    }
                ],
                "description": "Ajax Editable Category Product allows you to quick update products from category section."
            }
        ]
    }
}
