{
    "packages": {
        "connect20/fedobe_erostheme": [
            {
                "name": "connect20/Fedobe_Erostheme",
                "version": "1.0.0.1",
                "version_normalized": "1.0.0.1",
                "dist": {
                    "type": "tar",
                    "url": "https://connect20.magentocommerce.com/community/Fedobe_Erostheme/1.0.0.1/Fedobe_Erostheme-1.0.0.1.tgz"
                },
                "suggest": {
                    "magento-hackathon/magento-composer-installer": "Allows to manage this package as a dependency"
                },
                "type": "magento-module",
                "extra": {
                    "package-xml": "package.xml"
                },
                "license": [
                    "OSL-v3.0"
                ],
                "authors": [
                    {
                        "name": "Fedobe Solutions Pvt. Ltd",
                        "email": "mail@fedobe.com"
                    }
                ],
                "description": "Fedobe Eros free theme for Magento"
            },
            {
                "name": "connect20/Fedobe_Erostheme",
                "version": "1.0.0.2",
                "version_normalized": "1.0.0.2",
                "dist": {
                    "type": "tar",
                    "url": "https://connect20.magentocommerce.com/community/Fedobe_Erostheme/1.0.0.2/Fedobe_Erostheme-1.0.0.2.tgz"
                },
                "suggest": {
                    "magento-hackathon/magento-composer-installer": "Allows to manage this package as a dependency"
                },
                "type": "magento-module",
                "extra": {
                    "package-xml": "package.xml"
                },
                "license": [
                    "OSL-v3.0"
                ],
                "authors": [
                    {
                        "name": "Fedobe Solutions Pvt. Ltd",
                        "email": "mail@fedobe.com"
                    }
                ],
                "description": "Fedobe Eros free theme for Magento"
            }
        ]
    }
}
