{
    "packages": {
        "connect20/zapper_scantocheckout": [
            {
                "name": "connect20/zapper_scantocheckout",
                "version": "1.0.0",
                "version_normalized": "1.0.0.0",
                "dist": {
                    "type": "tar",
                    "url": "https://connect20.magentocommerce.com/community/zapper_scantocheckout/1.0.0/zapper_scantocheckout-1.0.0.tgz"
                },
                "require": {
                    "connect20/zapper_scantologin": ">=1.0.0"
                },
                "suggest": {
                    "magento-hackathon/magento-composer-installer": "Allows to manage this package as a dependency"
                },
                "type": "magento-module",
                "extra": {
                    "package-xml": "package.xml"
                },
                "license": [
                    "GNU-General-Public-License-(GPL)"
                ],
                "authors": [
                    {
                        "name": "Branden",
                        "email": "branden.paine@ota.co.za"
                    }
                ],
                "description": "Zapper for eCommerce checkout integration.\r\nFrictionless checkout framework via mobile device."
            }
        ]
    }
}
