{
    "packages": {
        "inchoo/php7": [
            {
                "name": "inchoo/php7",
                "version": "0.2.0",
                "version_normalized": "0.2.0.0",
                "source": {
                    "type": "git",
                    "url": "https://github.com/Inchoo/Inchoo_PHP7.git",
                    "reference": "6edf619cea94b4f4344587112c930d4df0b7cd2e"
                },
                "dist": {
                    "type": "zip",
                    "url": "https://api.github.com/repos/Inchoo/Inchoo_PHP7/zipball/6edf619cea94b4f4344587112c930d4df0b7cd2e",
                    "reference": "6edf619cea94b4f4344587112c930d4df0b7cd2e",
                    "shasum": ""
                },
                "time": "2015-12-15T08:08:42+00:00",
                "type": "magento-module",
                "license": [
                    "MIT"
                ],
                "authors": [
                    {
                        "name": "Ivan Čurdinjaković"
                    }
                ],
                "description": "PHP 7 compatibility extension for Magento 1 by Inchoo",
                "support": {
                    "source": "https://github.com/Inchoo/Inchoo_PHP7/tree/0.2.0",
                    "issues": "https://github.com/Inchoo/Inchoo_PHP7/issues"
                }
            },
            {
                "name": "inchoo/php7",
                "version": "0.3.0",
                "version_normalized": "0.3.0.0",
                "source": {
                    "type": "git",
                    "url": "https://github.com/Inchoo/Inchoo_PHP7.git",
                    "reference": "a411e38b1217cfa338d7e0dce052874831da6ae9"
                },
                "dist": {
                    "type": "zip",
                    "url": "https://api.github.com/repos/Inchoo/Inchoo_PHP7/zipball/a411e38b1217cfa338d7e0dce052874831da6ae9",
                    "reference": "a411e38b1217cfa338d7e0dce052874831da6ae9",
                    "shasum": ""
                },
                "time": "2015-12-18T10:50:19+00:00",
                "type": "magento-module",
                "license": [
                    "MIT"
                ],
                "authors": [
                    {
                        "name": "Ivan Čurdinjaković"
                    }
                ],
                "description": "PHP 7 compatibility extension for Magento 1 by Inchoo",
                "support": {
                    "source": "https://github.com/Inchoo/Inchoo_PHP7/tree/0.3.0",
                    "issues": "https://github.com/Inchoo/Inchoo_PHP7/issues"
                }
            },
            {
                "name": "inchoo/php7",
                "version": "0.3.1",
                "version_normalized": "0.3.1.0",
                "source": {
                    "type": "git",
                    "url": "https://github.com/Inchoo/Inchoo_PHP7.git",
                    "reference": "42fb93c39993e896cac8571596cf4b022b1f8391"
                },
                "dist": {
                    "type": "zip",
                    "url": "https://api.github.com/repos/Inchoo/Inchoo_PHP7/zipball/42fb93c39993e896cac8571596cf4b022b1f8391",
                    "reference": "42fb93c39993e896cac8571596cf4b022b1f8391",
                    "shasum": ""
                },
                "time": "2015-12-18T12:09:06+00:00",
                "type": "magento-module",
                "license": [
                    "MIT"
                ],
                "authors": [
                    {
                        "name": "Ivan Čurdinjaković"
                    }
                ],
                "description": "PHP 7 compatibility extension for Magento 1 by Inchoo",
                "support": {
                    "source": "https://github.com/Inchoo/Inchoo_PHP7/tree/0.3.1",
                    "issues": "https://github.com/Inchoo/Inchoo_PHP7/issues"
                }
            },
            {
                "name": "inchoo/php7",
                "version": "0.3.2",
                "version_normalized": "0.3.2.0",
                "source": {
                    "type": "git",
                    "url": "https://github.com/Inchoo/Inchoo_PHP7.git",
                    "reference": "1136ae3c6e7d19a314ba8d2ae75dadaa655b45b8"
                },
                "dist": {
                    "type": "zip",
                    "url": "https://api.github.com/repos/Inchoo/Inchoo_PHP7/zipball/1136ae3c6e7d19a314ba8d2ae75dadaa655b45b8",
                    "reference": "1136ae3c6e7d19a314ba8d2ae75dadaa655b45b8",
                    "shasum": ""
                },
                "require": {
                    "magento-hackathon/magento-composer-installer": "*"
                },
                "time": "2016-02-22T08:37:52+00:00",
                "type": "magento-module",
                "license": [
                    "MIT"
                ],
                "authors": [
                    {
                        "name": "Ivan Čurdinjaković"
                    }
                ],
                "description": "PHP 7 compatibility extension for Magento 1 by Inchoo",
                "support": {
                    "source": "https://github.com/Inchoo/Inchoo_PHP7/tree/0.3.2",
                    "issues": "https://github.com/Inchoo/Inchoo_PHP7/issues"
                }
            },
            {
                "name": "inchoo/php7",
                "version": "1.0.3",
                "version_normalized": "1.0.3.0",
                "source": {
                    "type": "git",
                    "url": "https://github.com/Inchoo/Inchoo_PHP7.git",
                    "reference": "df2a17eb5d928162518561a00244bcc6bcc2e552"
                },
                "dist": {
                    "type": "zip",
                    "url": "https://api.github.com/repos/Inchoo/Inchoo_PHP7/zipball/df2a17eb5d928162518561a00244bcc6bcc2e552",
                    "reference": "df2a17eb5d928162518561a00244bcc6bcc2e552",
                    "shasum": ""
                },
                "require": {
                    "magento-hackathon/magento-composer-installer": "*"
                },
                "time": "2016-04-28T09:00:03+00:00",
                "type": "magento-module",
                "license": [
                    "MIT"
                ],
                "authors": [
                    {
                        "name": "Ivan Čurdinjaković"
                    }
                ],
                "description": "PHP 7 compatibility extension for Magento 1 by Inchoo",
                "support": {
                    "source": "https://github.com/Inchoo/Inchoo_PHP7/tree/1.0.3",
                    "issues": "https://github.com/Inchoo/Inchoo_PHP7/issues"
                }
            },
            {
                "name": "inchoo/php7",
                "version": "1.0.4",
                "version_normalized": "1.0.4.0",
                "source": {
                    "type": "git",
                    "url": "https://github.com/Inchoo/Inchoo_PHP7.git",
                    "reference": "5c431e01d2c2344ed68a9eac190446bfc272b6cd"
                },
                "dist": {
                    "type": "zip",
                    "url": "https://api.github.com/repos/Inchoo/Inchoo_PHP7/zipball/5c431e01d2c2344ed68a9eac190446bfc272b6cd",
                    "reference": "5c431e01d2c2344ed68a9eac190446bfc272b6cd",
                    "shasum": ""
                },
                "require": {
                    "magento-hackathon/magento-composer-installer": "*"
                },
                "time": "2016-08-03T10:44:01+00:00",
                "type": "magento-module",
                "license": [
                    "MIT"
                ],
                "authors": [
                    {
                        "name": "Ivan Čurdinjaković"
                    }
                ],
                "description": "PHP 7 compatibility extension for Magento 1 by Inchoo",
                "support": {
                    "source": "https://github.com/Inchoo/Inchoo_PHP7/tree/1.0.4",
                    "issues": "https://github.com/Inchoo/Inchoo_PHP7/issues"
                }
            },
            {
                "name": "inchoo/php7",
                "version": "1.0.5",
                "version_normalized": "1.0.5.0",
                "source": {
                    "type": "git",
                    "url": "https://github.com/Inchoo/Inchoo_PHP7.git",
                    "reference": "879e0987ad3fd0cef0dec06b19689e98dc8f64ea"
                },
                "dist": {
                    "type": "zip",
                    "url": "https://api.github.com/repos/Inchoo/Inchoo_PHP7/zipball/879e0987ad3fd0cef0dec06b19689e98dc8f64ea",
                    "reference": "879e0987ad3fd0cef0dec06b19689e98dc8f64ea",
                    "shasum": ""
                },
                "require": {
                    "magento-hackathon/magento-composer-installer": "*"
                },
                "time": "2016-08-19T07:38:32+00:00",
                "type": "magento-module",
                "license": [
                    "MIT"
                ],
                "authors": [
                    {
                        "name": "Ivan Čurdinjaković"
                    }
                ],
                "description": "PHP 7 compatibility extension for Magento 1 by Inchoo",
                "support": {
                    "source": "https://github.com/Inchoo/Inchoo_PHP7/tree/1.0.5",
                    "issues": "https://github.com/Inchoo/Inchoo_PHP7/issues"
                }
            },
            {
                "name": "inchoo/php7",
                "version": "1.0.6",
                "version_normalized": "1.0.6.0",
                "source": {
                    "type": "git",
                    "url": "https://github.com/Inchoo/Inchoo_PHP7.git",
                    "reference": "717d0904429b0930cbcc6a6c8f19b7dadeb07aff"
                },
                "dist": {
                    "type": "zip",
                    "url": "https://api.github.com/repos/Inchoo/Inchoo_PHP7/zipball/717d0904429b0930cbcc6a6c8f19b7dadeb07aff",
                    "reference": "717d0904429b0930cbcc6a6c8f19b7dadeb07aff",
                    "shasum": ""
                },
                "require": {
                    "magento-hackathon/magento-composer-installer": "*"
                },
                "time": "2016-09-08T06:30:06+00:00",
                "type": "magento-module",
                "license": [
                    "MIT"
                ],
                "authors": [
                    {
                        "name": "Ivan Čurdinjaković"
                    }
                ],
                "description": "PHP 7 compatibility extension for Magento 1 by Inchoo",
                "support": {
                    "source": "https://github.com/Inchoo/Inchoo_PHP7/tree/1.0.6",
                    "issues": "https://github.com/Inchoo/Inchoo_PHP7/issues"
                }
            },
            {
                "name": "inchoo/php7",
                "version": "1.0.7",
                "version_normalized": "1.0.7.0",
                "source": {
                    "type": "git",
                    "url": "https://github.com/Inchoo/Inchoo_PHP7.git",
                    "reference": "584e10f62546b6fcbb5a57d59b1bbcb0fc3f9b42"
                },
                "dist": {
                    "type": "zip",
                    "url": "https://api.github.com/repos/Inchoo/Inchoo_PHP7/zipball/584e10f62546b6fcbb5a57d59b1bbcb0fc3f9b42",
                    "reference": "584e10f62546b6fcbb5a57d59b1bbcb0fc3f9b42",
                    "shasum": ""
                },
                "require": {
                    "magento-hackathon/magento-composer-installer": "*"
                },
                "time": "2017-02-02T11:55:48+00:00",
                "type": "magento-module",
                "license": [
                    "MIT"
                ],
                "authors": [
                    {
                        "name": "Ivan Čurdinjaković"
                    }
                ],
                "description": "PHP 7 compatibility extension for Magento 1 by Inchoo",
                "support": {
                    "source": "https://github.com/Inchoo/Inchoo_PHP7/tree/1.0.7",
                    "issues": "https://github.com/Inchoo/Inchoo_PHP7/issues"
                }
            },
            {
                "name": "inchoo/php7",
                "version": "1.1.0",
                "version_normalized": "1.1.0.0",
                "source": {
                    "type": "git",
                    "url": "https://github.com/Inchoo/Inchoo_PHP7.git",
                    "reference": "8d6f7c60c7cef1906d887a71d7a1bd04b9018aec"
                },
                "dist": {
                    "type": "zip",
                    "url": "https://api.github.com/repos/Inchoo/Inchoo_PHP7/zipball/8d6f7c60c7cef1906d887a71d7a1bd04b9018aec",
                    "reference": "8d6f7c60c7cef1906d887a71d7a1bd04b9018aec",
                    "shasum": ""
                },
                "require": {
                    "magento-hackathon/magento-composer-installer": "*"
                },
                "suggest": {
                    "phpseclib/mcrypt_compat": "PHP 7.1 polyfill for the mcrypt extension from PHP <= 7.0."
                },
                "time": "2017-04-05T11:00:06+00:00",
                "type": "magento-module",
                "license": [
                    "MIT"
                ],
                "authors": [
                    {
                        "name": "Ivan Čurdinjaković"
                    }
                ],
                "description": "PHP 7 compatibility extension for Magento 1 by Inchoo",
                "support": {
                    "issues": "https://github.com/Inchoo/Inchoo_PHP7/issues",
                    "wiki": "https://github.com/Inchoo/Inchoo_PHP7/wiki",
                    "source": "https://github.com/Inchoo/Inchoo_PHP7"
                }
            },
            {
                "name": "inchoo/php7",
                "version": "2.0.0",
                "version_normalized": "2.0.0.0",
                "source": {
                    "type": "git",
                    "url": "https://github.com/Inchoo/Inchoo_PHP7.git",
                    "reference": "5ce61485afc2f4559c05fb57116a418555d1ef6a"
                },
                "dist": {
                    "type": "zip",
                    "url": "https://api.github.com/repos/Inchoo/Inchoo_PHP7/zipball/5ce61485afc2f4559c05fb57116a418555d1ef6a",
                    "reference": "5ce61485afc2f4559c05fb57116a418555d1ef6a",
                    "shasum": ""
                },
                "require": {
                    "magento-hackathon/magento-composer-installer": "*"
                },
                "time": "2016-10-18T10:53:54+00:00",
                "type": "magento-module",
                "license": [
                    "MIT"
                ],
                "authors": [
                    {
                        "name": "Ivan Čurdinjaković"
                    }
                ],
                "description": "PHP 7 compatibility extension for Magento 1 by Inchoo",
                "support": {
                    "source": "https://github.com/Inchoo/Inchoo_PHP7/tree/2.0.0",
                    "issues": "https://github.com/Inchoo/Inchoo_PHP7/issues"
                }
            },
            {
                "name": "inchoo/php7",
                "version": "2.0.1",
                "version_normalized": "2.0.1.0",
                "source": {
                    "type": "git",
                    "url": "https://github.com/Inchoo/Inchoo_PHP7.git",
                    "reference": "a38b9005181b54e2542c952e39d1d28e27cc9014"
                },
                "dist": {
                    "type": "zip",
                    "url": "https://api.github.com/repos/Inchoo/Inchoo_PHP7/zipball/a38b9005181b54e2542c952e39d1d28e27cc9014",
                    "reference": "a38b9005181b54e2542c952e39d1d28e27cc9014",
                    "shasum": ""
                },
                "require": {
                    "magento-hackathon/magento-composer-installer": "*"
                },
                "time": "2017-02-02T12:04:13+00:00",
                "type": "magento-module",
                "license": [
                    "MIT"
                ],
                "authors": [
                    {
                        "name": "Ivan Čurdinjaković"
                    }
                ],
                "description": "PHP 7 compatibility extension for Magento 1 by Inchoo",
                "support": {
                    "source": "https://github.com/Inchoo/Inchoo_PHP7/tree/2.0.1",
                    "issues": "https://github.com/Inchoo/Inchoo_PHP7/issues"
                }
            },
            {
                "name": "inchoo/php7",
                "version": "2.1.0",
                "version_normalized": "2.1.0.0",
                "source": {
                    "type": "git",
                    "url": "https://github.com/Inchoo/Inchoo_PHP7.git",
                    "reference": "f89dac4003bfddf3affe78ad9f1098830e6225b1"
                },
                "dist": {
                    "type": "zip",
                    "url": "https://api.github.com/repos/Inchoo/Inchoo_PHP7/zipball/f89dac4003bfddf3affe78ad9f1098830e6225b1",
                    "reference": "f89dac4003bfddf3affe78ad9f1098830e6225b1",
                    "shasum": ""
                },
                "require": {
                    "magento-hackathon/magento-composer-installer": "*"
                },
                "suggest": {
                    "phpseclib/mcrypt_compat": "PHP 7.1 polyfill for the mcrypt extension from PHP <= 7.0."
                },
                "time": "2017-04-05T11:12:25+00:00",
                "type": "magento-module",
                "license": [
                    "MIT"
                ],
                "authors": [
                    {
                        "name": "Ivan Čurdinjaković"
                    }
                ],
                "description": "PHP 7 compatibility extension for Magento 1 by Inchoo",
                "support": {
                    "issues": "https://github.com/Inchoo/Inchoo_PHP7/issues",
                    "wiki": "https://github.com/Inchoo/Inchoo_PHP7/wiki",
                    "source": "https://github.com/Inchoo/Inchoo_PHP7"
                }
            },
            {
                "name": "inchoo/php7",
                "version": "2.1.1",
                "version_normalized": "2.1.1.0",
                "source": {
                    "type": "git",
                    "url": "https://github.com/Inchoo/Inchoo_PHP7.git",
                    "reference": "cd68a8cf7ed3dcd34c926d9f87fc0e440c3a4b82"
                },
                "dist": {
                    "type": "zip",
                    "url": "https://api.github.com/repos/Inchoo/Inchoo_PHP7/zipball/cd68a8cf7ed3dcd34c926d9f87fc0e440c3a4b82",
                    "reference": "cd68a8cf7ed3dcd34c926d9f87fc0e440c3a4b82",
                    "shasum": ""
                },
                "require": {
                    "magento-hackathon/magento-composer-installer": "*"
                },
                "suggest": {
                    "phpseclib/mcrypt_compat": "PHP 7.1 polyfill for the mcrypt extension from PHP <= 7.0."
                },
                "time": "2017-06-07T09:26:19+00:00",
                "type": "magento-module",
                "license": [
                    "MIT"
                ],
                "authors": [
                    {
                        "name": "Ivan Čurdinjaković"
                    }
                ],
                "description": "PHP 7 compatibility extension for Magento 1 by Inchoo",
                "support": {
                    "issues": "https://github.com/Inchoo/Inchoo_PHP7/issues",
                    "wiki": "https://github.com/Inchoo/Inchoo_PHP7/wiki",
                    "source": "https://github.com/Inchoo/Inchoo_PHP7"
                }
            }
        ]
    }
}
